pymytest/__init__.py
pymytest/tester.py
pymytest/tester_cli.py
pymytest-0.7.dist-info/METADATA
pymytest-0.7.dist-info/WHEEL
pymytest-0.7.dist-info/entry_points.txt
pymytest-0.7.dist-info/top_level.txt
pymytest-0.7.dist-info/RECORD
