Metadata-Version: 2.1
Name: pymytest
Version: 0.7
Summary: Python package that allows you to test APIs from the command line
Home-page: https://github.com/prasadjivane/pymytest
Author: Prasad Jivane
Author-email: prasadjivane@gmail.com
Requires-Dist: requests
